.gitignore
LICENSE
plot_experiments_results.sh
readme.md
readthedocs.yml
setup.cfg
setup.py
travis_setup.sh
sderl/__init__.py
sderl/run.py
sderl/user_config.py
sderl/version.py
sderl.egg-info/PKG-INFO
sderl.egg-info/SOURCES.txt
sderl.egg-info/dependency_links.txt
sderl.egg-info/requires.txt
sderl.egg-info/top_level.txt
sderl/algos/__init__.py
sderl/algos/pytorch/ddpg/core.py
sderl/algos/pytorch/ddpg/ddpg.py
sderl/algos/pytorch/dppo/act.pt
sderl/algos/pytorch/dppo/core.py
sderl/algos/pytorch/dppo/dppo.py
sderl/algos/pytorch/dppo/obs.pt
sderl/algos/pytorch/dppo/test_dppo.sh
sderl/algos/pytorch/dppo/test_hvp.py
sderl/algos/pytorch/dppo/test_nn_hvp.py
sderl/algos/pytorch/dvpg/core.py
sderl/algos/pytorch/dvpg/dvpg.py
sderl/algos/pytorch/dvpg/run_LunarLander.py
sderl/algos/pytorch/ppo/core.py
sderl/algos/pytorch/ppo/ppo.py
sderl/algos/pytorch/sac/core.py
sderl/algos/pytorch/sac/sac.py
sderl/algos/pytorch/sac_atari/core.py
sderl/algos/pytorch/sac_atari/sac.py
sderl/algos/pytorch/sderl/LICENSE
sderl/algos/pytorch/sderl/README.md
sderl/algos/pytorch/sderl/config.py
sderl/algos/pytorch/sderl/core.py
sderl/algos/pytorch/sderl/main.py
sderl/algos/pytorch/sderl/pde.py
sderl/algos/pytorch/sderl/ppo.py
sderl/algos/pytorch/sderl/solver.py
sderl/algos/pytorch/sderl/pde-gym/README.md
sderl/algos/pytorch/sderl/pde-gym/setup.py
sderl/algos/pytorch/sderl/pde-gym/pde_gym/__init__.py
sderl/algos/pytorch/sderl/pde-gym/pde_gym/setup.py
sderl/algos/pytorch/sderl/pde-gym/pde_gym.egg-info/PKG-INFO
sderl/algos/pytorch/sderl/pde-gym/pde_gym.egg-info/SOURCES.txt
sderl/algos/pytorch/sderl/pde-gym/pde_gym.egg-info/dependency_links.txt
sderl/algos/pytorch/sderl/pde-gym/pde_gym.egg-info/requires.txt
sderl/algos/pytorch/sderl/pde-gym/pde_gym.egg-info/top_level.txt
sderl/algos/pytorch/sderl/pde-gym/pde_gym/envs/AllenCahn.py
sderl/algos/pytorch/sderl/pde-gym/pde_gym/envs/HJB.py
sderl/algos/pytorch/sderl/pde-gym/pde_gym/envs/PricingOption.py
sderl/algos/pytorch/sderl/pde-gym/pde_gym/envs/__init__.py
sderl/algos/pytorch/sderl/pde-gym/pde_gym/pde_gym.egg-info/PKG-INFO
sderl/algos/pytorch/sderl/pde-gym/pde_gym/pde_gym.egg-info/SOURCES.txt
sderl/algos/pytorch/sderl/pde-gym/pde_gym/pde_gym.egg-info/dependency_links.txt
sderl/algos/pytorch/sderl/pde-gym/pde_gym/pde_gym.egg-info/requires.txt
sderl/algos/pytorch/sderl/pde-gym/pde_gym/pde_gym.egg-info/top_level.txt
sderl/algos/pytorch/td3/core.py
sderl/algos/pytorch/td3/td3.py
sderl/algos/pytorch/trpo/trpo.py
sderl/algos/pytorch/vpg/core.py
sderl/algos/pytorch/vpg/run_LunarLander.py
sderl/algos/pytorch/vpg/vpg.py
sderl/examples/pytorch/bench_ppo_cartpole.py
sderl/examples/pytorch/pg_math/1_simple_pg.py
sderl/examples/pytorch/pg_math/2_rtg_pg.py
sderl/examples/tf1/bench_ppo_cartpole.py
sderl/examples/tf1/train_mnist.py
sderl/examples/tf1/pg_math/1_simple_pg.py
