Metadata-Version: 1.1
Name: sderl
Version: 0.2.0
Summary: research on stochastic differential equations and deep RL.
Home-page: https://github.com/XiaohanZhangCMU/sderl.git
Author: Xiaohan Zhang
Author-email: UNKNOWN
License: UNKNOWN
Download-URL: https://github.com/XiaohanZhangCMU/sderl/archive/0.1.tar.gz
Platform: UNKNOWN
